bumbo/__init__.py
bumbo/api.py
bumbo/middleware.py
bumbo/response.py
bumbo_guyincognito-0.0.21.dist-info/METADATA
bumbo_guyincognito-0.0.21.dist-info/WHEEL
bumbo_guyincognito-0.0.21.dist-info/top_level.txt
bumbo_guyincognito-0.0.21.dist-info/RECORD
